Mongodb_to_Elastic_Search/Insert.py
Mongodb_to_Elastic_Search/__init__.py
Mongodb_to_Elastic_Search-1.0.0.dist-info/METADATA
Mongodb_to_Elastic_Search-1.0.0.dist-info/WHEEL
Mongodb_to_Elastic_Search-1.0.0.dist-info/top_level.txt
Mongodb_to_Elastic_Search-1.0.0.dist-info/RECORD
