Metadata-Version: 2.1
Name: Mongodb-to-Elastic-Search
Version: 1.0.0
Summary: Data Transfer from mongodb to Elastic search
Home-page: https://github.com/Aditya0025/Data-Transfer-Mongodb-to-Elastic-Search
Author: Aditya
Author-email: aditya0025@yahoo.com
License: MIT
Platform: UNKNOWN
Classifier: License :: OSI Approved :: MIT License
Classifier: Programming Language :: Python :: 3 
Requires-Dist: feedparser
Requires-Dist: html2text
